aiofilelock/__init__.py
aiofilelock-1.0.0.dist-info/DESCRIPTION.rst
aiofilelock-1.0.0.dist-info/METADATA
aiofilelock-1.0.0.dist-info/RECORD
aiofilelock-1.0.0.dist-info/WHEEL
aiofilelock-1.0.0.dist-info/metadata.json
aiofilelock-1.0.0.dist-info/top_level.txt
